{
  "required": true,
  "package": "com.rosemods.windswept.core.mixin",
  "compatibilityLevel": "JAVA_17",
  "minVersion": "0.8",
  "refmap": "windswept.refmap.json",
  "mixins": [
    "FoxMixin",
    "BoatMixin",
    "SolidBucketItemMixin",
    "PowderSnowBlockMixin",
    "LiquidBlockMixin",
    "BlockMixin",
    "LivingEntityMixin",
    "SnowLayerBlockMixin",
    "TreeFeaturesMixin",
    "TreeConfigurationBuilderMixin",
    "TreeFeatureMixin",
    "WitherRoseBlockMixin",
    "FoxEatBerriesGoalMixin",
    "TrunkPlacerMixin",
    "FlowerBlockMixin"
  ],
  "client": [
    "client.LivingEntityRendererMixin",
    "client.RabbitRendererMixin"
  ],
  "injectors": {
    "defaultRequire": 1
  }
}
